[{"Year":1998,"Value":54.56,"Units":"Percentage (%) of national budget"},{"Year":1999,"Value":55.31,"Units":"Percentage (%) of national budget"},{"Year":2000,"Value":55.13,"Units":"Percentage (%) of national budget"},{"Year":2001,"Value":55.03,"Units":"Percentage (%) of national budget"},{"Year":2002,"Value":57.54,"Units":"Percentage (%) of national budget"},{"Year":2003,"Value":58.53,"Units":"Percentage (%) of national budget"},{"Year":2004,"Value":59.02,"Units":"Percentage (%) of national budget"},{"Year":2005,"Value":60.13,"Units":"Percentage (%) of national budget"},{"Year":2006,"Value":58.61,"Units":"Percentage (%) of national budget"},{"Year":2007,"Value":57.71,"Units":"Percentage (%) of national budget"},{"Year":2008,"Value":43.71,"Units":"Percentage (%) of national budget"},{"Year":2009,"Value":55.1,"Units":"Percentage (%) of national budget"},{"Year":2010,"Value":53.0,"Units":"Percentage (%) of national budget"},{"Year":2011,"Value":57.36,"Units":"Percentage (%) of national budget"},{"Year":2012,"Value":56.46,"Units":"Percentage (%) of national budget"},{"Year":2013,"Value":57.09,"Units":"Percentage (%) of national budget"},{"Year":2014,"Value":55.84,"Units":"Percentage (%) of national budget"},{"Year":2015,"Value":56.84,"Units":"Percentage (%) of national budget"},{"Year":2016,"Value":52.49,"Units":"Percentage (%) of national budget"},{"Year":2017,"Value":57.37,"Units":"Percentage (%) of national budget"},{"Year":2018,"Value":56.67,"Units":"Percentage (%) of national budget"},{"Year":2019,"Value":59.16,"Units":"Percentage (%) of national budget"},{"Year":1998,"Value":22.18,"Units":"Percentage (%) of Gross Domestic Product (GDP)"},{"Year":1999,"Value":22.88,"Units":"Percentage (%) of Gross Domestic Product (GDP)"},{"Year":2000,"Value":22.59,"Units":"Percentage (%) of Gross Domestic Product (GDP)"},{"Year":2001,"Value":22.85,"Units":"Percentage (%) of Gross Domestic Product (GDP)"},{"Year":2002,"Value":24.64,"Units":"Percentage (%) of Gross Domestic Product (GDP)"},{"Year":2003,"Value":25.93,"Units":"Percentage (%) of Gross Domestic Product (GDP)"},{"Year":2004,"Value":25.14,"Units":"Percentage (%) of Gross Domestic Product (GDP)"},{"Year":2005,"Value":24.84,"Units":"Percentage (%) of Gross Domestic Product (GDP)"},{"Year":2006,"Value":23.87,"Units":"Percentage (%) of Gross Domestic Product (GDP)"},{"Year":2007,"Value":23.42,"Units":"Percentage (%) of Gross Domestic Product (GDP)"},{"Year":2008,"Value":23.83,"Units":"Percentage (%) of Gross Domestic Product (GDP)"},{"Year":2009,"Value":26.11,"Units":"Percentage (%) of Gross Domestic Product (GDP)"},{"Year":2010,"Value":25.33,"Units":"Percentage (%) of Gross Domestic Product (GDP)"},{"Year":2011,"Value":25.37,"Units":"Percentage (%) of Gross Domestic Product (GDP)"},{"Year":2012,"Value":24.74,"Units":"Percentage (%) of Gross Domestic Product (GDP)"},{"Year":2013,"Value":24.21,"Units":"Percentage (%) of Gross Domestic Product (GDP)"},{"Year":2014,"Value":24.47,"Units":"Percentage (%) of Gross Domestic Product (GDP)"},{"Year":2015,"Value":23.59,"Units":"Percentage (%) of Gross Domestic Product (GDP)"},{"Year":2016,"Value":23.26,"Units":"Percentage (%) of Gross Domestic Product (GDP)"},{"Year":2017,"Value":24.83,"Units":"Percentage (%) of Gross Domestic Product (GDP)"},{"Year":2018,"Value":24.93,"Units":"Percentage (%) of Gross Domestic Product (GDP)"},{"Year":2019,"Value":25.7,"Units":"Percentage (%) of Gross Domestic Product (GDP)"}]